whatsapp_business_api/__init__.py
whatsapp_business_api/api.py
whatsapp_business_api/endpoints.py
whatsapp_business_api/exceptions.py
whatsapp_business_api/types.py
whatsapp_business_api-0.1.4.dist-info/WHEEL
whatsapp_business_api-0.1.4.dist-info/METADATA
whatsapp_business_api-0.1.4.dist-info/RECORD
